flask_autoapi/__init__.py
flask_autoapi/restful_service_enroll.py
flask_autoapi/exceptions/__init__.py
flask_auto_api-1.0.8.dist-info/METADATA
flask_auto_api-1.0.8.dist-info/WHEEL
flask_auto_api-1.0.8.dist-info/top_level.txt
flask_auto_api-1.0.8.dist-info/RECORD
