Metadata-Version: 2.1
Name: flask-auto-api
Version: 1.0.8
Summary: Provide non-intrusive and one-click machine learning api release tool.
Home-page: https://github.com/Ecohnoch/flask_autoapi
Author: Ecohnoch
Author-email: chuyuan@ruc.edu.cn
Maintainer: Ecohnoch
Maintainer-email: chuyuan@ruc.edu.cn
License: BSD License
Platform: all
Classifier: Development Status :: 4 - Beta
Classifier: Operating System :: OS Independent
Classifier: Intended Audience :: Developers
Classifier: License :: OSI Approved :: BSD License
Classifier: Programming Language :: Python :: 3.6
Classifier: Topic :: Software Development :: Libraries
